aesp/__init__.py
aesp/constant.py
aesp/calculator/__init__.py
aesp/calculator/abacus.py
aesp/calculator/base.py
aesp/calculator/cp2k.py
aesp/calculator/dpmd.py
aesp/calculator/emt.py
aesp/calculator/gaussian.py
aesp/calculator/gulp.py
aesp/calculator/matgl.py
aesp/calculator/vasp.py
aesp/calculator/template/dpmd.py
aesp/calculator/template/emt.py
aesp/calculator/template/matgl.py
aesp/configs/__init__.py
aesp/configs/dflow.py
aesp/configs/inputs.py
aesp/configs/opt_params.py
aesp/configs/stage.py
aesp/configs/step.py
aesp/configs/step_base.py
aesp/entrypoint/__init__.py
aesp/entrypoint/analysis.py
aesp/entrypoint/download.py
aesp/entrypoint/main.py
aesp/entrypoint/resubmit.py
aesp/entrypoint/status.py
aesp/entrypoint/submit.py
aesp/entrypoint/watch.py
aesp/func/__init__.py
aesp/func/args_setup.py
aesp/func/database.py
aesp/func/entrypoint_func.py
aesp/func/population.py
aesp/func/scheduler.py
aesp/func/traj_render.py
aesp/gui/__init__.py
aesp/gui/atoms_info.py
aesp/gui/gui.py
aesp/operator/__init__.py
aesp/operator/base.py
aesp/operator/crossover/__init__.py
aesp/operator/crossover/base.py
aesp/operator/crossover/cylinder.py
aesp/operator/crossover/plane.py
aesp/operator/crossover/sphere.py
aesp/operator/generator/base.py
aesp/operator/generator/random.py
aesp/operator/mutation/__init__.py
aesp/operator/mutation/base.py
aesp/operator/mutation/permutation.py
aesp/operator/mutation/ripple.py
aesp/operator/mutation/strain.py
aesp/structure/__init__.py
aesp/structure/base.py
aesp/structure/bulk.py
aesp/structure/cluster.py
aesp/structure/layer.py
aesp/utils/__init__.py
aesp/utils/deepmd.py
aesp/utils/dispatcher.py
aesp/utils/dpgen2.py
aesp/utils/plotly_graph.py
aesp/utils/run_command.py
aesp/utils/tool.py
aesp/workflow/__init__.py
aesp/workflow/op/gen_structure.py
aesp/workflow/op/model_devi.py
aesp/workflow/op/prep_run_calc.py
aesp/workflow/op/run_dp_train.py
aesp/workflow/op/scheduler.py
aesp/workflow/superop/calc_block.py
aesp/workflow/superop/csp_block.py
aesp-2025.9.12.dist-info/licenses/LICENSE
aesp-2025.9.12.dist-info/METADATA
aesp-2025.9.12.dist-info/WHEEL
aesp-2025.9.12.dist-info/entry_points.txt
aesp-2025.9.12.dist-info/top_level.txt
aesp-2025.9.12.dist-info/RECORD
