Metadata-Version: 2.4
Name: aesp
Version: 2025.9.12
Summary: aesp(Adaptive Evolutionary Structure Predictor) is a crystal structure prediction tool written in Python.
Author-email: Chenglong Qin <clqin@foxmail.com>
Maintainer-email: Chenglong Qin <clqin@foxmail.com>
License: MIT License
Project-URL: Documentation, https://clqin-newbie.github.io/aesp/
Project-URL: Repository, https://github.com/clqin-newbie/aesp.git
Project-URL: Issues, https://github.com/clqin-newbie/aesp/issues
Keywords: CSP,DL
Classifier: Programming Language :: Python :: 3
Requires-Python: >=3.8
License-File: LICENSE
Requires-Dist: pyxtal
Requires-Dist: pydflow
Requires-Dist: dargs
Requires-Dist: dscribe
Requires-Dist: art
Requires-Dist: dpdata
Requires-Dist: dpdispatcher
Requires-Dist: nicegui
Provides-Extra: docs
Requires-Dist: sphinx; extra == "docs"
Requires-Dist: sphinx-book-theme; extra == "docs"
Requires-Dist: sphinx-argparse; extra == "docs"
Requires-Dist: dargs; extra == "docs"
Requires-Dist: myst_parser; extra == "docs"
Dynamic: license-file
